[
  [
    {
      "hours": "08:30",
      "date": "01/30/2024"
    },
    {
      "hours": "10:00",
      "date": "01/30/2024"
    },
    "Traitement images"
  ],
  [
    {
      "hours": "13:15",
      "date": "04/29/2024"
    },
    {
      "hours": "14:45",
      "date": "04/29/2024"
    },
    "Architecture - TD"
  ],
  [
    {
      "hours": "13:15",
      "date": "03/18/2024"
    },
    {
      "hours": "14:45",
      "date": "03/18/2024"
    },
    "Architecture - TD"
  ],
  [
    {
      "hours": "15:00",
      "date": "04/29/2024"
    },
    {
      "hours": "16:30",
      "date": "04/29/2024"
    },
    "Architecture - TD"
  ],
  [
    {
      "hours": "08:30",
      "date": "04/30/2024"
    },
    {
      "hours": "10:00",
      "date": "04/30/2024"
    },
    "Traitement images"
  ],
  [
    {
      "hours": "08:00",
      "date": "03/19/2024"
    },
    {
      "hours": "11:45",
      "date": "03/19/2024"
    },
    "ANAV - TD"
  ],
  [
    {
      "hours": "10:00",
      "date": "01/30/2024"
    },
    {
      "hours": "11:30",
      "date": "01/30/2024"
    },
    "MVFA TD"
  ],
  [
    {
      "hours": "08:15",
      "date": "02/20/2024"
    },
    {
      "hours": "12:15",
      "date": "02/20/2024"
    },
    "Atelier ConferENS"
  ],
  [
    {
      "hours": "08:00",
      "date": "10/24/2023"
    },
    {
      "hours": "12:00",
      "date": "10/24/2023"
    },
    "Atelier ConferENS"
  ]
]