[
  [
    {
      "hours": "13:30",
      "date": "11/21/2023"
    },
    {
      "hours": "15:30",
      "date": "11/21/2023"
    },
    "MLB soutenance projet"
  ],
  [
    {
      "hours": "14:00",
      "date": "10/03/2023"
    },
    {
      "hours": "17:00",
      "date": "10/03/2023"
    },
    "Module B - Séquence 1 : Continuité hydro-sédimentaire & restauration des cours d'eau"
  ],
  [
    {
      "hours": "09:45",
      "date": "01/25/2024"
    },
    {
      "hours": "11:15",
      "date": "01/25/2024"
    },
    "2IA CM"
  ],
  [
    {
      "hours": "08:00",
      "date": "11/10/2023"
    },
    {
      "hours": "11:15",
      "date": "11/10/2023"
    },
    "UE4 - Travaux de groupe"
  ],
  [
    {
      "hours": "16:45",
      "date": "09/14/2023"
    },
    {
      "hours": "18:15",
      "date": "09/14/2023"
    },
    "TD Physique subatomique"
  ],
  [
    {
      "hours": "13:15",
      "date": "01/29/2024"
    },
    {
      "hours": "17:15",
      "date": "01/29/2024"
    },
    "TP Projets Gr A et B"
  ],
  [
    {
      "hours": "09:45",
      "date": "02/02/2024"
    },
    {
      "hours": "11:15",
      "date": "02/02/2024"
    },
    "UE 2.2 FPB"
  ],
  [
    {
      "hours": "08:00",
      "date": "02/13/2024"
    },
    {
      "hours": "12:00",
      "date": "02/13/2024"
    },
    "TP ESP"
  ],
  [
    {
      "hours": "09:45",
      "date": "02/23/2024"
    },
    {
      "hours": "11:15",
      "date": "02/23/2024"
    },
    "UE 2.2 FPB"
  ],
  [
    {
      "hours": "13:15",
      "date": "09/26/2023"
    },
    {
      "hours": "16:30",
      "date": "09/26/2023"
    },
    "TD IPA"
  ],
  [
    {
      "hours": "13:15",
      "date": "09/19/2023"
    },
    {
      "hours": "16:30",
      "date": "09/19/2023"
    },
    "MS1-CM-TD"
  ],
  [
    {
      "hours": "09:00",
      "date": "02/15/2024"
    },
    {
      "hours": "13:00",
      "date": "02/15/2024"
    },
    "UC1.4 - Examen IBIS"
  ],
  [
    {
      "hours": "08:00",
      "date": "01/16/2024"
    },
    {
      "hours": "09:30",
      "date": "01/16/2024"
    },
    "UE4TD - Techniques de communication\\, Pro'fil"
  ],
  [
    {
      "hours": "16:45",
      "date": "10/25/2023"
    },
    {
      "hours": "18:15",
      "date": "10/25/2023"
    },
    "TD BOB"
  ]
]